jstsconverter/__init__.py
jstsconverter/converter.py
jstsconverter/prompts.py
jstsconverter/version.py
jstsconverter-0.1.3.dist-info/METADATA
jstsconverter-0.1.3.dist-info/WHEEL
jstsconverter-0.1.3.dist-info/top_level.txt
jstsconverter-0.1.3.dist-info/RECORD
